Workbook
Name JR_PAGE_ANCHOR_0_1: #REF!

Sheet Attivo
C1: Prestiti | F1: Titoli diversi da Azioni | M1: Azioni e Partecipazioni
F2: Residenti in altri paesi aerea Euro | I2: Residenti in Italia | L2: Resto del Mondo | M2: Residenti in altri paesi area Euro | O2: Resto del Mondo | P2: Residenti in Italia
A3: Data | B3: Cassa | C3: Residenti | D3: Residenti EU | E3: Resto del Mondo | F3: Altri residenti | G3: Amministrazioni Pubbliche | H3: IFM | I3: Altri residenti | J3: IFM | K3: Amministrazioni Pubbliche | L3: Resto del Mondo | M3: Altri residenti | N3: IFM | O3: Resto del Mondo | P3: Altri Residenti | Q3: IFM | R3: Quote di partecipazione in fondi monetari | S3: Immobilizzazioni | T3: Altre Attività
A4: 45016 | B4: 8989.16 | C4: 2267648.8 | D4: 156661.39 | E4: 98985.95 | F4: 13658.43 | G4: 81647.22 | H4: 26861.86 | I4: 150777.09 | J4: 48302.11 | K4: 392317.89 | L4: 66422.32 | M4: 14258.39 | N4: 40344.71 | O4: 15485.63 | P4: 79392.31 | Q4: 20839.37 | R4: 2.75 | S4: 81479.19 | T4: 362158.69
A5: =EDATE(A4,-1) -> 44985 | B5: 9270.75 | C5: 2296578.1 | D5: 148806.54 | E5: 96147.31 | F5: 14002.07 | G5: 80313.32 | H5: 26179.03 | I5: 151880.63 | J5: 48296.07 | K5: 390899.29 | L5: 65485.3 | M5: 14265.93 | N5: 40276.25 | O5: 15796.89 | P5: 78845.27 | Q5: 20691.29 | R5: 2.75 | S5: 81301.02 | T5: 382118.37
A6: =EDATE(A5,-1) -> 44954 | B6: 9481.6 | C6: 2311968.1 | D6: 151801.88 | E6: 97087.27 | F6: 14431.09 | G6: 78643.82 | H6: 25933.95 | I6: 152634.82 | J6: 48129.86 | K6: 384523.19 | L6: 63622.19 | M6: 14304.53 | N6: 40269.83 | O6: 15438.08 | P6: 78956.67 | Q6: 20678.01 | R6: 2.6 | S6: 81247.57 | T6: 356912.47
A7: =EDATE(A6,-1) -> 44923 | B7: 10441.82 | C7: 2303400.6 | D7: 158324.48 | E7: 96472.69 | F7: 13600.17 | G7: 75609.4 | H7: 24711.34 | I7: 154292.77 | J7: 47909.45 | K7: 376284.33 | L7: 62954.14 | M7: 14242.67 | N7: 38244.58 | O7: 17264.79 | P7: 79004.99 | Q7: 20593.33 | R7: 2.12 | S7: 81232.33 | T7: 390169.11
A8: =EDATE(A7,-1) -> 44893 | B8: 9565.69 | C8: 2401369 | D8: 152531.52 | E8: 103328.72 | F8: 14965.7 | G8: 77588.49 | H8: 25381.48 | I8: 139166.32 | J8: 49491.37 | K8: 393130.8 | L8: 64082.29 | M8: 14379.48 | N8: 38292.24 | O8: 18303.64 | P8: 79489.95 | Q8: 20644.56 | R8: 2.11 | S8: 81027.2 | T8: 359372.38
A9: =EDATE(A8,-1) -> 44862 | B9: 9651.38 | C9: 2394365 | D9: 154065.05 | E9: 107267.57 | F9: 14807.49 | G9: 76162.45 | H9: 23541.89 | I9: 136868.31 | J9: 48284.39 | K9: 395375.28 | L9: 64171.33 | M9: 14266.91 | N9: 38436.99 | O9: 18509.69 | P9: 79551.43 | Q9: 21728.99 | R9: 2.11 | S9: 80209.59 | T9: 369994.15
A10: =EDATE(A9,-1) -> 44832 | B10: 9837.78 | C10: 2387757 | D10: 160999.73 | E10: 109517.28 | F10: 15244.88 | G10: 73858.35 | H10: 24222.56 | I10: 140023.08 | J10: 48455.49 | K10: 386992.69 | L10: 64261.85 | M10: 14062.62 | N10: 38388.02 | O10: 18728.65 | P10: 79469.38 | Q10: 21674.57 | R10: 2.11 | S10: 75757.17 | T10: 381434.46
A11: =EDATE(A10,-1) -> 44801 | B11: 9907.1 | C11: 2406655.9 | D11: 151076.94 | E11: 111041 | F11: 15240.63 | G11: 74327.48 | H11: 24489.07 | I11: 140123.5 | J11: 48813.39 | K11: 403268.28 | L11: 65942.91 | M11: 14557.89 | N11: 38380.26 | O11: 18456.38 | P11: 79617.52 | Q11: 22012.37 | R11: 2.11 | S11: 75876.02 | T11: 338346.61
A12: =EDATE(A11,-1) -> 44770 | B12: 9848.02 | C12: 2411086.8 | D12: 156631.47 | E12: 111996.35 | F12: 15463.59 | G12: 76913.14 | H12: 25161.32 | I12: 143341.3 | J12: 48589.66 | K12: 415174.91 | L12: 65747.77 | M12: 14619.26 | N12: 38374.08 | O12: 18400.02 | P12: 79881.45 | Q12: 21956.3 | R12: 1.87 | S12: 75881.8 | T12: 306824.4
A13: =EDATE(A12,-1) -> 44740 | B13: 9828.72 | C13: 2411094.3 | D13: 146377.98 | E13: 109812.72 | F13: 15351.88 | G13: 76332.93 | H13: 24640.56 | I13: 145029.16 | J13: 48277.27 | K13: 412083.74 | L13: 62730.37 | M13: 14896.36 | N13: 38355.98 | O13: 18577.03 | P13: 76948.04 | Q13: 21809.39 | R13: 1.87 | S13: 75625.73 | T13: 314752.15
A14: =EDATE(A13,-1) -> 44709 | B14: 9648.55 | C14: 2479511.1 | D14: 148699.03 | E14: 105181.75 | F14: 15963.19 | G14: 77703.56 | H14: 24755.03 | I14: 146047.1 | J14: 49756.72 | K14: 417449.46 | L14: 62766.35 | M14: 15200.36 | N14: 38338.39 | O14: 18016.59 | P14: 78063.94 | Q14: 21273.42 | R14: 1.88 | S14: 76004.69 | T14: 292044.96
A15: =EDATE(A14,-1) -> 44679 | B15: 9889.53 | C15: 2470412.1 | D15: 149426.08 | E15: 106279.21 | F15: 16045.94 | G15: 75961.86 | H15: 24475.02 | I15: 146990.28 | J15: 50040.13 | K15: 422164.52 | L15: 62057.42 | M15: 15078.32 | N15: 38334.28 | O15: 17844.33 | P15: 74203.33 | Q15: 21308.3 | R15: 1.88 | S15: 75851.49 | T15: 287868.89
A16: =EDATE(A15,-1) -> 44648 | B16: 9241.69 | C16: 2460271.9 | D16: 146765.75 | E16: 107190.69 | F16: 15878.75 | G16: 78282.07 | H16: 24487.51 | I16: 143764.17 | J16: 51036.17 | K16: 426263.69 | L16: 62140.07 | M16: 14919.11 | N16: 38250.05 | O16: 17592.16 | P16: 74448.87 | Q16: 22045.15 | R16: 1.64 | S16: 75441.84 | T16: 259946.97
... A331: =EDATE(A330,-1) -> 35061 | B331: 4529.33 | C331: 776500.56 | D331: 43201.33 | E331: 74761.04 | F331: 755.88 | G331: 704.27 | H331: 642.47 | I331: 1927.93 | J331: 26043.89 | K331: 174447.26 | L331: 6483.91 | M331: 1662.56 | N331: 2228.51 | O331: 2023.31 | P331: 13185.66 | Q331: 13293.08 | R331: 0 | S331: 43043.07 | T331: 235156.84

Sheet Attivo_Sintetico
A1: Data | B1: Prestiti | C1: Titoli Diversi da Azioni | D1: Azioni | E1: Altro
A2: 45016 | B2: =Attivo!C4+Attivo!D4+Attivo!E4 -> 2523296.1 | C2: =Attivo!I4+Attivo!J4+Attivo!K4+Attivo!F4+Attivo!G4+Attivo!H4 -> 713564.6 | D2: =Attivo!L4+Attivo!M4+Attivo!N4+Attivo!O4+Attivo!P4+Attivo!Q4+Attivo!R4 -> 236745.48 | E2: =Attivo!S4+Attivo!T4+Attivo!B4 -> 452627.04
A3: 44985 | B3: =Attivo!C5+Attivo!D5+Attivo!E5 -> 2541532 | C3: =Attivo!I5+Attivo!J5+Attivo!K5+Attivo!F5+Attivo!G5+Attivo!H5 -> 711570.41 | D3: =Attivo!L5+Attivo!M5+Attivo!N5+Attivo!O5+Attivo!P5+Attivo!Q5+Attivo!R5 -> 235363.68 | E3: =Attivo!S5+Attivo!T5+Attivo!B5 -> 472690.14
A4: 44954 | B4: =Attivo!C6+Attivo!D6+Attivo!E6 -> 2560857.3 | C4: =Attivo!I6+Attivo!J6+Attivo!K6+Attivo!F6+Attivo!G6+Attivo!H6 -> 704296.73 | D4: =Attivo!L6+Attivo!M6+Attivo!N6+Attivo!O6+Attivo!P6+Attivo!Q6+Attivo!R6 -> 233271.91 | E4: =Attivo!S6+Attivo!T6+Attivo!B6 -> 447641.64
A5: 44923 | B5: =Attivo!C7+Attivo!D7+Attivo!E7 -> 2558197.7 | C5: =Attivo!I7+Attivo!J7+Attivo!K7+Attivo!F7+Attivo!G7+Attivo!H7 -> 692407.46 | D5: =Attivo!L7+Attivo!M7+Attivo!N7+Attivo!O7+Attivo!P7+Attivo!Q7+Attivo!R7 -> 232306.62 | E5: =Attivo!S7+Attivo!T7+Attivo!B7 -> 481843.26
A6: 44893 | B6: =Attivo!C8+Attivo!D8+Attivo!E8 -> 2657229.2 | C6: =Attivo!I8+Attivo!J8+Attivo!K8+Attivo!F8+Attivo!G8+Attivo!H8 -> 699724.16 | D6: =Attivo!L8+Attivo!M8+Attivo!N8+Attivo!O8+Attivo!P8+Attivo!Q8+Attivo!R8 -> 235194.27 | E6: =Attivo!S8+Attivo!T8+Attivo!B8 -> 449965.27
A7: 44862 | B7: =Attivo!C9+Attivo!D9+Attivo!E9 -> 2655697.6 | C7: =Attivo!I9+Attivo!J9+Attivo!K9+Attivo!F9+Attivo!G9+Attivo!H9 -> 695039.81 | D7: =Attivo!L9+Attivo!M9+Attivo!N9+Attivo!O9+Attivo!P9+Attivo!Q9+Attivo!R9 -> 236667.45 | E7: =Attivo!S9+Attivo!T9+Attivo!B9 -> 459855.12
A8: 44832 | B8: =Attivo!C10+Attivo!D10+Attivo!E10 -> 2658274 | C8: =Attivo!I10+Attivo!J10+Attivo!K10+Attivo!F10+Attivo!G10+Attivo!H10 -> 688797.05 | D8: =Attivo!L10+Attivo!M10+Attivo!N10+Attivo!O10+Attivo!P10+Attivo!Q10+Attivo!R10 -> 236587.2 | E8: =Attivo!S10+Attivo!T10+Attivo!B10 -> 467029.41
A9: 44801 | B9: =Attivo!C11+Attivo!D11+Attivo!E11 -> 2668773.9 | C9: =Attivo!I11+Attivo!J11+Attivo!K11+Attivo!F11+Attivo!G11+Attivo!H11 -> 706262.35 | D9: =Attivo!L11+Attivo!M11+Attivo!N11+Attivo!O11+Attivo!P11+Attivo!Q11+Attivo!R11 -> 238969.44 | E9: =Attivo!S11+Attivo!T11+Attivo!B11 -> 424129.73
A10: 44770 | B10: =Attivo!C12+Attivo!D12+Attivo!E12 -> 2679714.6 | C10: =Attivo!I12+Attivo!J12+Attivo!K12+Attivo!F12+Attivo!G12+Attivo!H12 -> 724643.92 | D10: =Attivo!L12+Attivo!M12+Attivo!N12+Attivo!O12+Attivo!P12+Attivo!Q12+Attivo!R12 -> 238980.75 | E10: =Attivo!S12+Attivo!T12+Attivo!B12 -> 392554.22
A11: 44740 | B11: =Attivo!C13+Attivo!D13+Attivo!E13 -> 2667285 | C11: =Attivo!I13+Attivo!J13+Attivo!K13+Attivo!F13+Attivo!G13+Attivo!H13 -> 721715.54 | D11: =Attivo!L13+Attivo!M13+Attivo!N13+Attivo!O13+Attivo!P13+Attivo!Q13+Attivo!R13 -> 233319.04 | E11: =Attivo!S13+Attivo!T13+Attivo!B13 -> 400206.6
A12: 44709 | B12: =Attivo!C14+Attivo!D14+Attivo!E14 -> 2733391.9 | C12: =Attivo!I14+Attivo!J14+Attivo!K14+Attivo!F14+Attivo!G14+Attivo!H14 -> 731675.06 | D12: =Attivo!L14+Attivo!M14+Attivo!N14+Attivo!O14+Attivo!P14+Attivo!Q14+Attivo!R14 -> 233660.93 | E12: =Attivo!S14+Attivo!T14+Attivo!B14 -> 377698.2
A13: 44679 | B13: =Attivo!C15+Attivo!D15+Attivo!E15 -> 2726117.4 | C13: =Attivo!I15+Attivo!J15+Attivo!K15+Attivo!F15+Attivo!G15+Attivo!H15 -> 735677.75 | D13: =Attivo!L15+Attivo!M15+Attivo!N15+Attivo!O15+Attivo!P15+Attivo!Q15+Attivo!R15 -> 228827.86 | E13: =Attivo!S15+Attivo!T15+Attivo!B15 -> 373609.91
... A292: 36188 | B292: =Attivo!C294+Attivo!D294+Attivo!E294 -> 1045571.6 | C292: =Attivo!I294+Attivo!J294+Attivo!K294+Attivo!F294+Attivo!G294+Attivo!H294 -> 229726.87 | D292: =Attivo!L294+Attivo!M294+Attivo!N294+Attivo!O294+Attivo!P294+Attivo!Q294+Attivo!R294 -> 73901.11 | E292: =Attivo!S294+Attivo!T294+Attivo!B294 -> 249718.26

Sheet Conto Economico
A1: Data | B1: Interessi attivi | C1: Interessi passivi | D1: Interessi netti da derivati - contabilizzazione delle operazioni di copertura, rischio di tasso di interesse | E1: Margine di interesse | F1: Altri ricavi netti | G1: Utili o perdite (-) su attività detenute per negoziazione, al netto | H1: Utili o perdite (-) da commissioni e compensi, al netto | I1: Margine di intermediazione | J1: Costi operativi | K1: Costi per il personale | L1: Imposte indirette | M1: Risultato di gestione | N1: Utili o perdite da modifica | O1: Accantonamenti | P1: Riduzione di valore su attività finanziarie | Q1: Utili o (-) perdite straordinarie | R1: Utile o (-) perdita lordi | S1: Imposte dirette a debito o (-) a credito | T1: Utile o (-) perdita netti | U1: Dividendi, distribuiti | V1: Totale attività | W1: Totale attivo, media annuale | X1: Capitale e riserve | Y1: Capitale e riserve, media annuale | Z1: Dipendenti | AA1: Numero di dipendenti, media annuale | AB1: Numero di banche segnalanti | AC1: Costo unitario del personale (euro)
A2: 44561 | B2: 40767 | C2: 10487 | D2: -840 | E2: 30280 | F2: 42032 | G2: 1563 | H2: 27748 | I2: 72312 | J2: 47664 | K2: 24107 | L2: 4119 | M2: 24648 | N2: -65 | O2: 889 | P2: 9884 | Q2: 9066 | R2: 22876 | S2: 768 | T2: 22108 | U2: 6984 | V2: 3363394 | W2: 3306688 | X2: 247479 | Y2: 243264 | Z2: 269701 | AA2: 272291 | AB2: 449 | AC2: 88865
A3: =EDATE(A2,-12) -> 44196 | B3: 41403 | C3: 10682 | D3: -188 | E3: 30721 | F3: 40388 | G3: 1240 | H3: 24619 | I3: 71109 | J3: 48371 | K3: 25356 | L3: 3924 | M3: 22738 | N3: -84 | O3: 4072 | P3: 15831 | Q3: -5764 | R3: -3023 | S3: -217 | T3: -2806 | U3: 2873 | V3: 3212173 | W3: 3214728 | X3: 240263 | Y3: 241260 | Z3: 274753 | AA3: 277929 | AB3: 466 | AC3: 91405
A4: =EDATE(A3,-12) -> 43830 | B4: 45135 | C4: 13704 | D4: -605 | E4: 31431 | F4: 40762 | G4: 1243 | H4: 25545 | I4: 72193 | J4: 46991 | K4: 23576 | L4: 4049 | M4: 25202 | N4: -96 | O4: 479 | P4: 11837 | Q4: -59 | R4: 12736 | S4: 4248 | T4: 8488 | U4: 5358 | V4: 3116682 | W4: 3157970 | X4: 239171 | Y4: 239695 | Z4: 281207 | AA4: 281757 | AB4: 486 | AC4: 83386
A5: =EDATE(A4,-12) -> 43465 | B5: 47127 | C5: 13438 | D5: -3 | E5: 33689 | F5: 41094 | G5: 631 | H5: 26075 | I5: 74783 | J5: 47107 | K5: 22742 | L5: 3944 | M5: 27676 | N5: -97 | O5: 1503 | P5: 11759 | Q5: -1953 | R5: 12364 | S5: 92 | T5: 12272 | U5: 7006 | V5: 3077432 | W5: 3118523 | X5: 235089 | Y5: 243520 | Z5: 275020 | AA5: 279161 | AB5: 505 | AC5: 80690
A6: =EDATE(A5,-12) -> 43100 | B6: 51296 | C6: 20129 | D6: 246 | E6: 31167 | F6: 38323 | G6: 1538 | H6: 25621 | I6: 69491 | J6: 48645 | K6: 24476 | L6: 3954 | M6: 20846 | O6: 2265 | P6: 20690 | Q6: 17013 | R6: 14905 | S6: -57 | T6: 14962 | U6: 5487 | V6: 3096076 | W6: 3121932 | X6: 259431 | Y6: 242105 | Z6: 283131 | AA6: 290717 | AB6: 539 | AC6: 83813
A7: =EDATE(A6,-12) -> 42735 | B7: 57182 | C7: 25243 | D7: 651 | E7: 31940 | F7: 38052 | G7: 1112 | H7: 25132 | I7: 69992 | J7: 53743 | K7: 25889 | L7: 4247 | M7: 16249 | O7: 2244 | P7: 33674 | Q7: 861 | R7: -18808 | S7: 311 | T7: -19120 | U7: 4854 | V7: 3118987 | W7: 3181258 | X7: 229461 | Y7: 247456 | Z7: 296614 | AA7: 298982 | AB7: 606 | AC7: 85824
A8: =EDATE(A7,-12) -> 42369 | B8: 59929 | C8: 27044 | D8: 855 | E8: 32885 | F8: 47522 | G8: 1933 | H8: 25578 | I8: 80407 | J8: 49955 | K8: 24700 | L8: 4277 | M8: 30452 | O8: 1779 | P8: 20937 | Q8: 2714 | R8: 10450 | S8: 405 | T8: 10045 | U8: 5851 | V8: 3143835 | W8: 3131455 | X8: 254095 | Y8: 251808 | Z8: 299646 | AA8: 300648 | AB8: 630 | AC8: 81308
A9: =EDATE(A8,-12) -> 42004 | B9: 70416 | C9: 36254 | D9: 963 | E9: 34162 | F9: 43320 | G9: 1331 | H9: 24131 | I9: 77482 | J9: 46745 | K9: 24177 | L9: 4000 | M9: 30737 | O9: 1029 | P9: 32688 | Q9: 1007 | R9: -1974 | S9: -1236 | T9: -737 | U9: 3400 | V9: 3130569 | W9: 3124411 | X9: 249109 | Y9: 251564 | Z9: 300716 | AA9: 305891 | AB9: 646 | AC9: 78933
A10: =EDATE(A9,-12) -> 41639 | B10: 76821 | C10: 43368 | D10: 1889 | E10: 33453 | F10: 43711 | G10: 1181 | H10: 22857 | I10: 77164 | J10: 45705 | K10: 23673 | L10: 3604 | M10: 31459 | O10: 1756 | P10: 34378 | Q10: 2595 | R10: -2080 | S10: -2975 | T10: 895 | U10: 2464 | V10: 3117031 | W10: 3259166 | X10: 244303 | Y10: 261719 | Z10: 307901 | AA10: 309692 | AB10: 671 | AC10: 75875
A11: =EDATE(A10,-12) -> 41274 | B11: 89073 | C11: 51494 | D11: 1958 | E11: 37579 | F11: 38791 | G11: 2638 | H11: 22485 | I11: 76370 | J11: 48163 | K11: 25552 | L11: 3054 | M11: 28207 | O11: 1399 | P11: 26550 | Q11: -36 | R11: 222 | S11: -2558 | T11: 2780 | U11: 3528 | V11: 3360096 | W11: 3360365 | X11: 267949 | Y11: 264490 | Z11: 310849 | AA11: 315328 | AB11: 697 | AC11: 79572
A12: =EDATE(A11,-12) -> 40908 | B12: 91270 | C12: 52615 | D12: 1686 | E12: 38655 | F12: 34269 | G12: -1155 | H12: 22751 | I12: 72924 | J12: 49154 | K12: 26230 | L12: 2906 | M12: 23770 | O12: 1310 | P12: 16718 | Q12: -2241 | R12: 3500 | S12: -1406 | T12: 4906 | U12: 3426 | V12: 3300038 | W12: 3246470 | X12: 257270 | Y12: 286296 | Z12: 317760 | AA12: 319500 | AB12: 728 | AC12: 80592
A13: =EDATE(A12,-12) -> 40543 | B13: 82601 | C13: 44028 | D13: 2921 | E13: 38574 | F13: 36064 | G13: -1310 | H13: 22860 | I13: 74638 | J13: 48525 | K13: 26021 | L13: 2718 | M13: 26113 | O13: 1443 | P13: 13797 | Q13: 721 | R13: 11594 | S13: 3168 | T13: 8426 | U13: 5327 | V13: 3216649 | W13: 3446877 | X13: 288256 | Y13: 297115 | Z13: 322405 | AA13: 322553 | AB13: 743 | AC13: 80044
A14: =EDATE(A13,-12) -> 40178 | B14: 106429 | C14: 64364 | D14: 700 | E14: 42065 | F14: 36099 | G14: 1044 | H14: 21267 | I14: 78164 | J14: 49469 | K14: 26032 | L14: 2720 | M14: 28694 | O14: 1258 | P14: 16311 | Q14: 146 | R14: 11271 | S14: 3685 | T14: 7587 | U14: 5280 | V14: 3468392 | W14: 3458752 | X14: 296799 | Y14: 288208 | Z14: 325143 | AA14: 331807 | AB14: 777 | AC14: 75724
A15: =EDATE(A14,-12) -> 39813 | B15: 166679 | C15: 120721 | D15: -2455 | E15: 45958 | F15: 35425 | G15: -3603 | H15: 20662 | I15: 81383 | J15: 51887 | K15: 27847 | L15: 2321 | M15: 29496 | O15: 1891 | P15: 13777 | Q15: 3598 | R15: 17427 | S15: 1419 | T15: 16008 | U15: 5586 | V15: 3414524 | W15: 3258620 | X15: 278966 | Y15: 284298 | Z15: 339447 | AA15: 339451 | AB15: 796 | AC15: 79658
A16: =EDATE(A15,-12) -> 39447 | B16: 136294 | C16: 93613 | D16: -452 | E16: 42681 | F16: 41285 | G16: 49 | H16: 21938 | I16: 83966 | J16: 50424 | K16: 27945 | L16: 2450 | M16: 33542 | O16: 1829 | P16: 7165 | Q16: 4834 | R16: 29382 | S16: 8718 | T16: 20664 | U16: 14011 | V16: 3090415 | W16: 2946660 | X16: 284278 | Y16: 255258 | Z16: 340470 | AA16: 341604 | AB16: 807 | AC16: 81857
A17: =EDATE(A16,-12) -> 39082 | B17: 103482 | C17: 63143 | D17: 764 | E17: 40339 | F17: 44371 | G17: 1926 | H17: 21832 | I17: 84710 | J17: 48555 | K17: 26385 | L17: 2601 | M17: 36155 | O17: 1593 | P17: 5919 | Q17: -161 | R17: 28482 | S17: 7779 | T17: 20703 | U17: 14439 | V17: 2707831 | W17: 2707831 | X17: 218942 | Y17: 218942 | Z17: 339138 | AA17: 338826 | AB17: 788 | AC17: 86834
A18: =EDATE(A17,-12) -> 38717 | L18: 2558 | U18: 12333 | Z18: 336080 | AA18: 336080

Sheet Depositi
B1: Estero | H1: Nazionali
A2: Data | B2: Resto del mondo | C2: CC | D2: Fino a 2 anni | E2: Oltre 2 anni | F2: Con preavviso | G2: Repo | H2: CC | I2: Fino a 2 anni | J2: Oltre 2 anni | K2: Con preavviso | L2: Repo
A3: 2023-03-31 | B3: 35989.79 | C3: 11037.21 | D3: 9300.98 | E3: 8256.25 | F3: 345.07 | G3: 2832.77 | H3: 1368648 | I3: 64528 | J3: 150734.98 | K3: 320552.23 | L3: 110806.42
A4: 2023-02-28 | B4: 38129.12 | C4: 11049.74 | D4: 8601.77 | E4: 8247.6 | F4: 342.35 | G4: 2514.8 | H4: 1384106.8 | I4: 55682.66 | J4: 151335.56 | K4: 321323.83 | L4: 113970.06
A5: 2023-01-31 | B5: 38879.93 | C5: 11342.6 | D5: 8613.42 | E5: 8195.62 | F5: 345.55 | G5: 1888.13 | H5: 1402724.7 | I5: 48957.49 | J5: 152077.35 | K5: 320316.86 | L5: 118563.06
A6: 2022-12-31 | B6: 35834.57 | C6: 10166.48 | D6: 8343.72 | E6: 8212.94 | F6: 350.78 | G6: 882.64 | H6: 1458155 | I6: 46336.9 | J6: 153115.97 | K6: 319474.42 | L6: 88458.14
A7: 2022-11-30 | B7: 38217.19 | C7: 10027.31 | D7: 7696.62 | E7: 8043.53 | F7: 368.45 | G7: 1081.06 | H7: 1424559.7 | I7: 43076.33 | J7: 138416.19 | K7: 317411.78 | L7: 114644.25
A8: 2022-10-31 | B8: 37538.66 | C8: 11757.18 | D8: 7287.7 | E8: 8094.11 | F8: 374.13 | G8: 1151.33 | H8: 1452489.5 | I8: 36682.22 | J8: 138042.43 | K8: 319452.02 | L8: 100698.57
A9: 2022-09-30 | B9: 38011 | C9: 13162.5 | D9: 7230.47 | E9: 8113.17 | F9: 367.15 | G9: 1092.05 | H9: 1461204.2 | I9: 32839.91 | J9: 141213.1 | K9: 319532.57 | L9: 94383.68
A10: 2022-08-31 | B10: 37571 | C10: 10607.8 | D10: 6951.7 | E10: 7861.34 | F10: 363.62 | G10: 1367.85 | H10: 1474819.1 | I10: 30492.34 | J10: 141712.09 | K10: 320610.33 | L10: 108151.41
A11: 2022-07-31 | B11: 37178 | C11: 12120.46 | D11: 6672.26 | E11: 7765.99 | F11: 368.35 | G11: 1698.5 | H11: 1496775.1 | I11: 29717.96 | J11: 144855.18 | K11: 319622.22 | L11: 106418.38
A12: 2022-06-30 | B12: 37217 | C12: 11158.46 | D12: 6423.88 | E12: 7968.87 | F12: 362.46 | G12: 969.52 | H12: 1465173.7 | I12: 30667.84 | J12: 146159.13 | K12: 318218.93 | L12: 101846.91
A13: 2022-05-31 | B13: 38696 | C13: 11192.62 | D13: 6113.25 | E13: 7851.49 | F13: 362.59 | G13: 2293.81 | H13: 1481261.5 | I13: 30990.45 | J13: 147553.74 | K13: 318978.44 | L13: 122387.63
A14: 2022-04-30 | B14: 37850 | C14: 12027.46 | D14: 6360.6 | E14: 7780.61 | F14: 363.13 | G14: 1539.87 | H14: 1485920.9 | I14: 31824.4 | J14: 148417.91 | K14: 318299.65 | L14: 122861.65
... A293: 1999-01-31 | B293: 24813 | C293: 1402.36 | D293: 6037.98 | E293: 299.52 | F293: 14.92 | G293: 275.8 | H293: 349442.35 | I293: 75705.81 | J293: 22544.47 | K293: 60832.05 | L293: 61320.41
A294: 1998-12-31
A295: 1998-11-30
A296: 1998-10-31
A297: 1998-09-30
A298: 1998-08-31
A299: 1998-07-31
A300: 1998-06-30
A301: 1998-05-31
A302: 1998-04-30
A303: 1998-03-31
A304: 1998-02-28
A305: 1998-01-31
... A330: 1995-12-31

Sheet Depositi_Sintetico
B1: Estero | E1: Nazionali
A2: Data | B2: Resto del mondo | C2: CC | D2: Tempo | E2: CC | F2: Tempo
A3: 45016 | B3: 35989.79 | C3: 11037.21 | D3: =Depositi!D3+Depositi!E3+Depositi!F3 -> 17902.3 | E3: 1368648 | F3: =Depositi!I3+Depositi!J3+Depositi!K3 -> 535815.21
A4: 44985 | B4: 38129.12 | C4: 11049.74 | D4: =Depositi!D4+Depositi!E4+Depositi!F4 -> 17191.72 | E4: 1384106.8 | F4: =Depositi!I4+Depositi!J4+Depositi!K4 -> 528342.05
A5: 44954 | B5: 38879.93 | C5: 11342.6 | D5: =Depositi!D5+Depositi!E5+Depositi!F5 -> 17154.59 | E5: 1402724.7 | F5: =Depositi!I5+Depositi!J5+Depositi!K5 -> 521351.7
A6: 44923 | B6: 35834.57 | C6: 10166.48 | D6: =Depositi!D6+Depositi!E6+Depositi!F6 -> 16907.44 | E6: 1458155 | F6: =Depositi!I6+Depositi!J6+Depositi!K6 -> 518927.29
A7: 44893 | B7: 38217.19 | C7: 10027.31 | D7: =Depositi!D7+Depositi!E7+Depositi!F7 -> 16108.6 | E7: 1424559.7 | F7: =Depositi!I7+Depositi!J7+Depositi!K7 -> 498904.3
A8: 44862 | B8: 37538.66 | C8: 11757.18 | D8: =Depositi!D8+Depositi!E8+Depositi!F8 -> 15755.94 | E8: 1452489.5 | F8: =Depositi!I8+Depositi!J8+Depositi!K8 -> 494176.67
A9: 44832 | B9: 38011 | C9: 13162.5 | D9: =Depositi!D9+Depositi!E9+Depositi!F9 -> 15710.79 | E9: 1461204.2 | F9: =Depositi!I9+Depositi!J9+Depositi!K9 -> 493585.58
A10: 44801 | B10: 37571 | C10: 10607.8 | D10: =Depositi!D10+Depositi!E10+Depositi!F10 -> 15176.66 | E10: 1474819.1 | F10: =Depositi!I10+Depositi!J10+Depositi!K10 -> 492814.76
A11: 44770 | B11: 37178 | C11: 12120.46 | D11: =Depositi!D11+Depositi!E11+Depositi!F11 -> 14806.6 | E11: 1496775.1 | F11: =Depositi!I11+Depositi!J11+Depositi!K11 -> 494195.36
A12: 44740 | B12: 37217 | C12: 11158.46 | D12: =Depositi!D12+Depositi!E12+Depositi!F12 -> 14755.21 | E12: 1465173.7 | F12: =Depositi!I12+Depositi!J12+Depositi!K12 -> 495045.9
A13: 44709 | B13: 38696 | C13: 11192.62 | D13: =Depositi!D13+Depositi!E13+Depositi!F13 -> 14327.33 | E13: 1481261.5 | F13: =Depositi!I13+Depositi!J13+Depositi!K13 -> 497522.63
A14: 44679 | B14: 37850 | C14: 12027.46 | D14: =Depositi!D14+Depositi!E14+Depositi!F14 -> 14504.34 | E14: 1485920.9 | F14: =Depositi!I14+Depositi!J14+Depositi!K14 -> 498541.96
... A293: 36188 | B293: 24813 | C293: 1402.36 | D293: =Depositi!D293+Depositi!E293+Depositi!F293 -> 6352.42 | E293: 349442.35 | F293: =Depositi!I293+Depositi!J293+Depositi!K293 -> 159082.33

Sheet Prestiti
B1: Residenti EU | H1: Residenti
A2: Data | B2: IFM resid. in altri stati membri UEM | C2: Amministrioni pubbliche residenti in altri stati membri UEM | D2: Assicurazioni, fondi pensione e altre istituzioni finanziarie di altri paesi dell'area euro - tutte le valute | E2: Famiglie | F2: Imprese non finanziarie | G2: Resto del mondo | H2: IFM | I2: Altre amm.pubbliche italiane | J2: Amministrazione centrale | K2: Altre istituzioni finanziarie | L2: Assicurazioni e fondi pensione | M2: Società non finanziarie | N2: Famiglie consumatrici | O2: Famiglie produttrici | P2: Istituzioni senza scopo di lucro
A3: 45016 | B3: 128225.28 | C3: 162.23 | D3: 12470.48 | E3: 833.93 | F3: 14969.48 | G3: 98985.95 | H3: 519930.22 | I3: 68566.71 | J3: 182746.42 | K3: 171093.55 | L3: 3333.47 | M3: 643124.4 | N3: 595098.67 | O3: 76058.48 | P3: 7696.89
A4: 44985 | B4: 121173.06 | C4: 159.83 | D4: 12278.37 | E4: 821.8 | F4: 14373.49 | G4: 96147.31 | H4: 547377.08 | I4: 68769.49 | J4: 183552.44 | K4: 170735.02 | L4: 3292.26 | M4: 643720.15 | N4: 594824.43 | O4: 76502 | P4: 7805.24
A5: 44954 | B5: 124130.89 | C5: 182.16 | D5: 11922.3 | E5: 801.66 | F5: 14764.88 | G5: 97087.27 | H5: 558970.47 | I5: 68702.28 | J5: 188013.11 | K5: 166429.01 | L5: 3442.71 | M5: 645868.24 | N5: 595677.85 | O5: 77024.41 | P5: 7840.04
A6: 44923 | B6: 131760.86 | C6: 218.45 | D6: 11807.5 | E6: 800.89 | F6: 13736.78 | G6: 96472.69 | H6: 532667.3 | I6: 67562.73 | J6: 195994.04 | K6: 175731.62 | L6: 3461.9 | M6: 647405.59 | N6: 595413.06 | O6: 77368.76 | P6: 7795.56
A7: 44893 | B7: 127221.56 | C7: 140.24 | D7: 9986.19 | E7: 793.23 | F7: 14390.3 | G7: 103328.72 | H7: 621864.53 | I7: 68100.48 | J7: 187343.74 | K7: 174335.64 | L7: 3477.3 | M7: 664506.2 | N7: 595881.03 | O7: 77883.03 | P7: 7977.06
A8: 44862 | B8: 128767.49 | C8: 167.74 | D8: 9841.56 | E8: 775.95 | F8: 14512.31 | G8: 107267.57 | H8: 619699.08 | I8: 67879.66 | J8: 192049.84 | K8: 163689.27 | L8: 3700.4 | M8: 667065.15 | N8: 594366.83 | O8: 78161.26 | P8: 7753.55
A9: 44832 | B9: 135001.76 | C9: 173.18 | D9: 9963.77 | E9: 774.16 | F9: 15086.86 | G9: 109517.28 | H9: 600759.5 | I9: 67801.82 | J9: 192877.84 | K9: 166559.59 | L9: 3885.61 | M9: 676490.01 | N9: 593102.21 | O9: 78640.71 | P9: 7639.72
A10: 44801 | B10: 127237.42 | C10: 124.64 | D10: 9135.03 | E10: 765.26 | F10: 13814.58 | G10: 111041 | H10: 617635.16 | I10: 67682.43 | J10: 193607.91 | K10: 167718.02 | L10: 4398.37 | M10: 678880.89 | N10: 590535.69 | O10: 78761.41 | P10: 7436.05
A11: 44770 | B11: 132554.34 | C11: 148.76 | D11: 9518.56 | E11: 757.29 | F11: 13652.52 | G11: 111996.35 | H11: 621395.73 | I11: 67846.68 | J11: 193058.48 | K11: 172043.69 | L11: 4734.84 | M11: 674044.67 | N11: 591604.73 | O11: 78918.49 | P11: 7439.5
A12: 44740 | B12: 121799.03 | C12: 168.08 | D12: 10308.78 | E12: 750.64 | F12: 13351.44 | G12: 109812.72 | H12: 627356.21 | I12: 68116.39 | J12: 194126.52 | K12: 172404.65 | L12: 5008.11 | M12: 668877.68 | N12: 588013.46 | O12: 79617.72 | P12: 7573.61
A13: 44709 | B13: 125616.23 | C13: 89.45 | D13: 10079.84 | E13: 737.45 | F13: 12176.06 | G13: 105181.75 | H13: 698972.21 | I13: 69202.83 | J13: 191339.09 | K13: 172361.83 | L13: 4941.26 | M13: 669862.55 | N13: 585030.66 | O13: 79927.69 | P13: 7873.02
A14: 44679 | B14: 126504.18 | C14: 92.46 | D14: 9747.91 | E14: 726.06 | F14: 12355.47 | G14: 106279.21 | H14: 695836.75 | I14: 69301.85 | J14: 192425.24 | K14: 177501.98 | L14: 5093.27 | M14: 660685.32 | N14: 582005.51 | O14: 79663.58 | P14: 7898.67
... A293: 36188 | B293: 63404.22 | C293: 60.71 | D293: 7896.97 | E293: 231.75 | F293: 1230.05 | G293: 90293.6 | H293: 126659.26 | I293: 24960.71 | J293: 37120.56 | K293: 96468.46 | L293: 3859.96 | M293: 398043.4 | N293: 133329.21 | O293: 55573.75 | P293: 6439.38
G294: 83440.02
G295: 89620.72
G296: 97052.94
G297: 95419.48
G298: 99740.45
G299: 97107.74
G300: 103406.31
G301: 96582.41
G302: 95466.54
G303: 100366.78
G304: 98529.91
G305: 97901.39
... G330: 74761.04

Sheet Prestiti Sintetico
A2: Data | B2: Altro EU | C2: EU | D2: Mondo | E2: ITA Fin | F2: ITA Gov | G2: ITA | H2: ITA+EU | I2: Totale
A3: 45016 | B3: =Prestiti!B3+Prestiti!C3+Prestiti!D3 -> 140857.99 | C3: =Prestiti!E3+Prestiti!F3 -> 15803.41 | D3: =Prestiti!G3 -> 98985.95 | E3: =Prestiti!H3+Prestiti!K3+Prestiti!L3 -> 694357.24 | F3: =Prestiti!I3+Prestiti!J3 -> 251313.13 | G3: =Prestiti!M3+Prestiti!N3+Prestiti!O3+Prestiti!P3 -> 1321978.4 | H3: =G3+C3 -> 1337781.8 | I3: =SUM(B3:G3) -> 2523296.2 | K3: =B3/I3*100 -> 5.5823011 | L3: =C3/I3*100 -> 0.62630024 | M3: =D3/I3*100 -> 3.9228828 | N3: =E3/I3*100 -> 27.517865 | O3: =F3/I3*100 -> 9.9597159 | P3: =G3/I3*100 -> 52.390935 | Q3: =H3/I3*100 -> 53.017235
A4: 44985 | B4: =Prestiti!B4+Prestiti!C4+Prestiti!D4 -> 133611.26 | C4: =Prestiti!E4+Prestiti!F4 -> 15195.29 | D4: =Prestiti!G4 -> 96147.31 | E4: =Prestiti!H4+Prestiti!K4+Prestiti!L4 -> 721404.36 | F4: =Prestiti!I4+Prestiti!J4 -> 252321.93 | G4: =Prestiti!M4+Prestiti!N4+Prestiti!O4+Prestiti!P4 -> 1322851.8 | H4: =G4+C4 -> 1338047.1 | I4: =SUM(B4:G4) -> 2541532 | K4: =B4/I4*100 -> 5.2571151 | L4: =C4/I4*100 -> 0.59787916 | M4: =D4/I4*100 -> 3.7830455 | N4: =E4/I4*100 -> 28.384627 | O4: =F4/I4*100 -> 9.9279463 | P4: =G4/I4*100 -> 52.049387 | Q4: =H4/I4*100 -> 52.647267
A5: 44954 | B5: =Prestiti!B5+Prestiti!C5+Prestiti!D5 -> 136235.35 | C5: =Prestiti!E5+Prestiti!F5 -> 15566.54 | D5: =Prestiti!G5 -> 97087.27 | E5: =Prestiti!H5+Prestiti!K5+Prestiti!L5 -> 728842.19 | F5: =Prestiti!I5+Prestiti!J5 -> 256715.39 | G5: =Prestiti!M5+Prestiti!N5+Prestiti!O5+Prestiti!P5 -> 1326410.5 | H5: =G5+C5 -> 1341977.1 | I5: =SUM(B5:G5) -> 2560857.3 | K5: =B5/I5*100 -> 5.3199119 | L5: =C5/I5*100 -> 0.60786441 | M5: =D5/I5*100 -> 3.7912019 | N5: =E5/I5*100 -> 28.460867 | O5: =F5/I5*100 -> 10.024588 | P5: =G5/I5*100 -> 51.795567 | Q5: =H5/I5*100 -> 52.403431
A6: 44923 | B6: =Prestiti!B6+Prestiti!C6+Prestiti!D6 -> 143786.81 | C6: =Prestiti!E6+Prestiti!F6 -> 14537.67 | D6: =Prestiti!G6 -> 96472.69 | E6: =Prestiti!H6+Prestiti!K6+Prestiti!L6 -> 711860.82 | F6: =Prestiti!I6+Prestiti!J6 -> 263556.77 | G6: =Prestiti!M6+Prestiti!N6+Prestiti!O6+Prestiti!P6 -> 1327983 | H6: =G6+C6 -> 1342520.6 | I6: =SUM(B6:G6) -> 2558197.7 | K6: =B6/I6*100 -> 5.6206293 | L6: =C6/I6*100 -> 0.56827781 | M6: =D6/I6*100 -> 3.7711194 | N6: =E6/I6*100 -> 27.826654 | O6: =F6/I6*100 -> 10.302439 | P6: =G6/I6*100 -> 51.910881 | Q6: =H6/I6*100 -> 52.479158
A7: 44893 | B7: =Prestiti!B7+Prestiti!C7+Prestiti!D7 -> 137347.99 | C7: =Prestiti!E7+Prestiti!F7 -> 15183.53 | D7: =Prestiti!G7 -> 103328.72 | E7: =Prestiti!H7+Prestiti!K7+Prestiti!L7 -> 799677.47 | F7: =Prestiti!I7+Prestiti!J7 -> 255444.22 | G7: =Prestiti!M7+Prestiti!N7+Prestiti!O7+Prestiti!P7 -> 1346247.3 | H7: =G7+C7 -> 1361430.9 | I7: =SUM(B7:G7) -> 2657229.2 | K7: =B7/I7*100 -> 5.1688423 | L7: =C7/I7*100 -> 0.57140459 | M7: =D7/I7*100 -> 3.8885888 | N7: =E7/I7*100 -> 30.09441 | O7: =F7/I7*100 -> 9.6131796 | P7: =G7/I7*100 -> 50.663574 | Q7: =H7/I7*100 -> 51.234979
A8: 44862 | B8: =Prestiti!B8+Prestiti!C8+Prestiti!D8 -> 138776.79 | C8: =Prestiti!E8+Prestiti!F8 -> 15288.26 | D8: =Prestiti!G8 -> 107267.57 | E8: =Prestiti!H8+Prestiti!K8+Prestiti!L8 -> 787088.75 | F8: =Prestiti!I8+Prestiti!J8 -> 259929.5 | G8: =Prestiti!M8+Prestiti!N8+Prestiti!O8+Prestiti!P8 -> 1347346.8 | H8: =G8+C8 -> 1362635.1 | I8: =SUM(B8:G8) -> 2655697.7 | K8: =B8/I8*100 -> 5.2256246 | L8: =C8/I8*100 -> 0.57567773 | M8: =D8/I8*100 -> 4.0391484 | N8: =E8/I8*100 -> 29.637739 | O8: =F8/I8*100 -> 9.7876164 | P8: =G8/I8*100 -> 50.734194 | Q8: =H8/I8*100 -> 51.309871
A9: 44832 | B9: =Prestiti!B9+Prestiti!C9+Prestiti!D9 -> 145138.71 | C9: =Prestiti!E9+Prestiti!F9 -> 15861.02 | D9: =Prestiti!G9 -> 109517.28 | E9: =Prestiti!H9+Prestiti!K9+Prestiti!L9 -> 771204.7 | F9: =Prestiti!I9+Prestiti!J9 -> 260679.66 | G9: =Prestiti!M9+Prestiti!N9+Prestiti!O9+Prestiti!P9 -> 1355872.6 | H9: =G9+C9 -> 1371733.7 | I9: =SUM(B9:G9) -> 2658274 | K9: =B9/I9*100 -> 5.4598852 | L9: =C9/I9*100 -> 0.5966661 | M9: =D9/I9*100 -> 4.1198642 | N9: =E9/I9*100 -> 29.011482 | O9: =F9/I9*100 -> 9.8063502 | P9: =G9/I9*100 -> 51.005752 | Q9: =H9/I9*100 -> 51.602418
A10: 44801 | B10: =Prestiti!B10+Prestiti!C10+Prestiti!D10 -> 136497.09 | C10: =Prestiti!E10+Prestiti!F10 -> 14579.84 | D10: =Prestiti!G10 -> 111041 | E10: =Prestiti!H10+Prestiti!K10+Prestiti!L10 -> 789751.55 | F10: =Prestiti!I10+Prestiti!J10 -> 261290.34 | G10: =Prestiti!M10+Prestiti!N10+Prestiti!O10+Prestiti!P10 -> 1355614 | H10: =G10+C10 -> 1370193.9 | I10: =SUM(B10:G10) -> 2668773.9 | K10: =B10/I10*100 -> 5.1145993 | L10: =C10/I10*100 -> 0.54631231 | M10: =D10/I10*100 -> 4.1607497 | N10: =E10/I10*100 -> 29.592299 | O10: =F10/I10*100 -> 9.7906512 | P10: =G10/I10*100 -> 50.795388 | Q10: =H10/I10*100 -> 51.3417
A11: 44770 | B11: =Prestiti!B11+Prestiti!C11+Prestiti!D11 -> 142221.66 | C11: =Prestiti!E11+Prestiti!F11 -> 14409.81 | D11: =Prestiti!G11 -> 111996.35 | E11: =Prestiti!H11+Prestiti!K11+Prestiti!L11 -> 798174.26 | F11: =Prestiti!I11+Prestiti!J11 -> 260905.16 | G11: =Prestiti!M11+Prestiti!N11+Prestiti!O11+Prestiti!P11 -> 1352007.4 | H11: =G11+C11 -> 1366417.2 | I11: =SUM(B11:G11) -> 2679714.6 | K11: =B11/I11*100 -> 5.3073435 | L11: =C11/I11*100 -> 0.53773674 | M11: =D11/I11*100 -> 4.1794133 | N11: =E11/I11*100 -> 29.785793 | O11: =F11/I11*100 -> 9.7363039 | P11: =G11/I11*100 -> 50.453409 | Q11: =H11/I11*100 -> 50.991146
A12: 44740 | B12: =Prestiti!B12+Prestiti!C12+Prestiti!D12 -> 132275.89 | C12: =Prestiti!E12+Prestiti!F12 -> 14102.08 | D12: =Prestiti!G12 -> 109812.72 | E12: =Prestiti!H12+Prestiti!K12+Prestiti!L12 -> 804768.97 | F12: =Prestiti!I12+Prestiti!J12 -> 262242.91 | G12: =Prestiti!M12+Prestiti!N12+Prestiti!O12+Prestiti!P12 -> 1344082.5 | H12: =G12+C12 -> 1358184.6 | I12: =SUM(B12:G12) -> 2667285 | K12: =B12/I12*100 -> 4.9591959 | L12: =C12/I12*100 -> 0.5287054 | M12: =D12/I12*100 -> 4.1170223 | N12: =E12/I12*100 -> 30.17184 | O12: =F12/I12*100 -> 9.8318292 | P12: =G12/I12*100 -> 50.391407 | Q12: =H12/I12*100 -> 50.920113
A13: 44709 | B13: =Prestiti!B13+Prestiti!C13+Prestiti!D13 -> 135785.52 | C13: =Prestiti!E13+Prestiti!F13 -> 12913.51 | D13: =Prestiti!G13 -> 105181.75 | E13: =Prestiti!H13+Prestiti!K13+Prestiti!L13 -> 876275.3 | F13: =Prestiti!I13+Prestiti!J13 -> 260541.92 | G13: =Prestiti!M13+Prestiti!N13+Prestiti!O13+Prestiti!P13 -> 1342693.9 | H13: =G13+C13 -> 1355607.4 | I13: =SUM(B13:G13) -> 2733391.9 | K13: =B13/I13*100 -> 4.9676564 | L13: =C13/I13*100 -> 0.47243536 | M13: =D13/I13*100 -> 3.8480303 | N13: =E13/I13*100 -> 32.058165 | O13: =F13/I13*100 -> 9.5318172 | P13: =G13/I13*100 -> 49.121895 | Q13: =H13/I13*100 -> 49.594331
A14: 44679 | B14: =Prestiti!B14+Prestiti!C14+Prestiti!D14 -> 136344.55 | C14: =Prestiti!E14+Prestiti!F14 -> 13081.53 | D14: =Prestiti!G14 -> 106279.21 | E14: =Prestiti!H14+Prestiti!K14+Prestiti!L14 -> 878432 | F14: =Prestiti!I14+Prestiti!J14 -> 261727.09 | G14: =Prestiti!M14+Prestiti!N14+Prestiti!O14+Prestiti!P14 -> 1330253.1 | H14: =G14+C14 -> 1343334.6 | I14: =SUM(B14:G14) -> 2726117.5 | K14: =B14/I14*100 -> 5.0014188 | L14: =C14/I14*100 -> 0.47985937 | M14: =D14/I14*100 -> 3.8985558 | N14: =E14/I14*100 -> 32.222823 | O14: =F14/I14*100 -> 9.6007268 | P14: =G14/I14*100 -> 48.796616 | Q14: =H14/I14*100 -> 49.276476
... A293: 36188 | B293: =Prestiti!B293+Prestiti!C293+Prestiti!D293 -> 71361.9 | C293: =Prestiti!E293+Prestiti!F293 -> 1461.8 | D293: =Prestiti!G293 -> 90293.6 | E293: =Prestiti!H293+Prestiti!K293+Prestiti!L293 -> 226987.68 | F293: =Prestiti!I293+Prestiti!J293 -> 62081.27 | G293: =Prestiti!M293+Prestiti!N293+Prestiti!O293+Prestiti!P293 -> 593385.74 | H293: =G293+C293 -> 594847.54 | I293: =SUM(B293:G293) -> 1045572 | K293: =B293/I293*100 -> 6.8251541 | L293: =C293/I293*100 -> 0.13980864 | M293: =D293/I293*100 -> 8.635809 | N293: =E293/I293*100 -> 21.709426 | O293: =F293/I293*100 -> 5.9375414 | P293: =G293/I293*100 -> 56.752261 | Q293: =H293/I293*100 -> 56.892069

Sheet Depositi_Tassi
A1: Data | B1: Tasso Depositi | C1: Tasso CC | D1: Tasso Tempo
A2: 45016 | B2: 0.5987 | C2: 0.2603 | D2: 2.1165
A3: 44985 | B3: 0.5437 | C3: 0.2164 | D3: 1.9015
A4: 44954 | B4: 0.4922 | C4: 0.1777 | D4: 1.6841
A5: 44923 | B5: 0.4535 | C5: 0.1465 | D5: 1.4986
A6: 44893 | B6: 0.4179 | C6: 0.1115 | D6: 1.2467
A7: 44862 | B7: 0.3677 | C7: 0.07 | D7: 1.0925
A8: 44832 | B8: 0.3438 | C8: 0.0498 | D8: 1.0086
A9: 44801 | B9: 0.3227 | C9: 0.0245 | D9: 0.9387
A10: 44770 | B10: 0.3167 | C10: 0.0234 | D10: 0.9065
A11: 44740 | B11: 0.315 | C11: 0.0204 | D11: 0.8879
A12: 44709 | B12: 0.3138 | C12: 0.0204 | D12: 0.895
A13: 44679 | B13: 0.318 | C13: 0.0203 | D13: 0.9264
... A244: 37649 | B244: 1.3117 | C244: 1.0193 | D244: 2.5168
A245: 37618 | B245: 1.395 | C245: 1.0939
A246: 37588 | B246: 1.5612 | C246: 1.2527
A247: 37557 | B247: 1.5635 | C247: 1.2247
A248: 37527 | B248: 1.6007 | C248: 1.2714
A249: 37496 | B249: 1.6225 | C249: 1.2807
A250: 37465 | B250: 1.6403 | C250: 1.3088
A251: 37435 | B251: 1.6425 | C251: 1.3181
A252: 37404 | B252: 1.6372 | C252: 1.2994
A253: 37374 | B253: 1.6137 | C253: 1.2807
A254: 37343 | B254: 1.6122 | C254: 1.2714
A255: 37315 | B255: 1.5979 | C255: 1.2621
A256: 37284 | B256: 1.5717 | C256: 1.234
... A292: 36188 | B292: 1.7584 | C292: 1.1967

Sheet Prestiti_Tassi
A1: Data | B1: Lungo Termine | C1: Breve Termine
A2: 45016 | B2: 4.0584 | C2: 4.3439
A3: 44985 | B3: 3.7347 | C3: 3.6779
A4: 44954 | B4: 3.8826 | C4: 3.7525
A5: 44923 | B5: 3.512 | C5: 3.538
A6: 44893 | B6: 3.6067 | C6: 2.9586
A7: 44862 | B7: 3.2601 | C7: 2.5736
A8: 44832 | B8: 2.4886 | C8: 2.0694
A9: 44801 | B9: 2.0541 | C9: 1.566
A10: 44770 | B10: 2.6961 | C10: 1.3973
A11: 44740 | B11: 2.3564 | C11: 1.4974
A12: 44709 | B12: 2.2487 | C12: 1.2571
A13: 44679 | B13: 2.1194 | C13: 1.2806
... A244: 37649 | B244: 4.4249 | C244: 5.2234

Sheet Passivo
B1: Depositi
B2: Residenti in Altri Paesi EU | F2: Residenti in Italia | J2: Resto del Mondo
A3: Data dell'osservazione | B3: Di cui in Euro | C3: Altri Residenti | D3: Amministrazioni Pubbliche | E3: IFM | F3: Di cui in Euro | G3: Altri Residenti | H3: IFM | I3: Amministrazioni Pubblica | J3: In Euro | K3: Totale | L3: Obbligazioni | M3: Capitale e Riserve | N3: Altre Passività
A4: 45016 | B4: 229467.96 | C4: 31770.57 | D4: 16.13 | E4: 229378.55 | F4: 2629398.8 | G4: 1992001.8 | H4: 613534.44 | I4: 49719.9 | J4: 53100.71 | K4: 73704.42 | L4: 266067.96 | M4: 348461.68 | N4: 321577.64
A5: =EDATE(A4,-1) -> 44985 | B5: 238979 | C5: 30753.57 | D5: 17.56 | E5: 243137.79 | F5: 2643718.4 | G5: 2003070.1 | H5: 615883.06 | I5: 49317.39 | J5: 55380.21 | K5: 74848.68 | L5: 261845.11 | M5: 346921.74 | N5: 335360.96
A6: =EDATE(A5,-1) -> 44954 | B6: 228858.51 | C6: 30382.48 | D6: 16.81 | E6: 231762.09 | F6: 2661515.8 | G6: 2019231.5 | H6: 618198.92 | I6: 49668.57 | J6: 55459.72 | K6: 75885.72 | L6: 255525.05 | M6: 344675.31 | N6: 320720.89
A7: =EDATE(A6,-1) -> 44923 | B7: 208945.34 | C7: 27953.89 | D7: 16.62 | E7: 210559.46 | F7: 2709774.9 | G7: 2042687.9 | H7: 646371.49 | I7: 47276.59 | J7: 51195.72 | K7: 72794.4 | L7: 256983.46 | M7: 342416.74 | N7: 317693.69
A8: =EDATE(A7,-1) -> 44893 | B8: 213503.07 | C8: 27213.02 | D8: 18.87 | E8: 219581.82 | F8: 2742150.2 | G8: 2016134.1 | H8: 697948.45 | I8: 54323.27 | J8: 55345.73 | K8: 75471.59 | L8: 257493.91 | M8: 344384.73 | N8: 349543.13
A9: =EDATE(A8,-1) -> 44862 | B9: 213207.88 | C9: 28659.21 | D9: 20.33 | E9: 220486.22 | F9: 2769037.8 | G9: 2025220.7 | H9: 719602.11 | I9: 51122.07 | J9: 52788.51 | K9: 74705.5 | L9: 254709.86 | M9: 344704.74 | N9: 328028.69
A10: =EDATE(A9,-1) -> 44832 | B10: 211335.72 | C10: 29960.28 | D10: 19.4 | E10: 214553 | F10: 2768505.1 | G10: 2027021 | H10: 719082.78 | I10: 48875.01 | J10: 55014.41 | K10: 78436.26 | L10: 252942.23 | M10: 343879.92 | N10: 335917.72
A11: =EDATE(A10,-1) -> 44801 | B11: 208703.05 | C11: 27147.27 | D11: 19.88 | E11: 218848.58 | F11: 2795147.2 | G11: 2052958 | H11: 716838.09 | I11: 52693.58 | J11: 56625.58 | K11: 78606.06 | L11: 249408.37 | M11: 338462.52 | N11: 303153.09
A12: =EDATE(A11,-1) -> 44770 | B12: 207755.28 | C12: 28620.61 | D12: 20.35 | E12: 215410.96 | F12: 2823755.7 | G12: 2075064.3 | H12: 723581.69 | I12: 52495.21 | J12: 52733.23 | K12: 76398.73 | L12: 248772.33 | M12: 338665.21 | N12: 276863.91
A13: =EDATE(A12,-1) -> 44740 | B13: 192210.29 | C13: 26877.05 | D13: 21.78 | E13: 199457.57 | F13: 2782771 | G13: 2040175.2 | H13: 719586.61 | I13: 50558.65 | J13: 54265.52 | K13: 76323.6 | L13: 249432.62 | M13: 342368.02 | N13: 317725.09
A14: =EDATE(A13,-1) -> 44709 | B14: 210903.38 | C14: 27805.26 | D14: 29.31 | E14: 215768.82 | F14: 2854696.5 | G14: 2079703.9 | H14: 751608.74 | I14: 50296.56 | J14: 56843.48 | K14: 77307.08 | L14: 247218.78 | M14: 340131.07 | N14: 286555.93
A15: =EDATE(A14,-1) -> 44679 | B15: 212144.15 | C15: 28066.1 | D15: 27.2 | E15: 217141.38 | F15: 2855794.3 | G15: 2085884.2 | H15: 746131.75 | I15: 50671.23 | J15: 56954.67 | K15: 78251.89 | L15: 248137.38 | M15: 337679.02 | N15: 272242.41
A16: =EDATE(A15,-1) -> 44648 | B16: 201819.27 | C16: 28173.69 | D16: 28.38 | E16: 206519.33 | F16: 2815662.4 | G16: 2040901.3 | H16: 750800.59 | I16: 50494.68 | J16: 58044.7 | K16: 77485.59 | L16: 249810.57 | M16: 345559.78 | N16: 278193.79
... A294: =EDATE(A293,-1) -> 36188 | B294: 86913.83 | C294: 8030.46 | D294: 168.24 | E294: 103944.25 | F294: 687194.54 | G294: 557685.7 | H294: 135218.2 | I294: 20576.68 | J294: 63635 | K294: 121704.65 | L294: 251157.05 | M294: 110458.52 | N294: 289974.12

Sheet Passivo_Sintetico
A1: Data | B1: Depositi Esteri | C1: Depositi Nazionali | D1: Obbligazioni | E1: Capitale e Riserve | F1: Altro
A2: 45016 | B2: =Passivo!C4+Passivo!D4+Passivo!E4+Passivo!K4 -> 334869.67 | C2: =Passivo!G4+Passivo!H4+Passivo!I4 -> 2655256.1 | D2: 266067.96 | E2: 348461.68 | F2: 321577.64
A3: =EDATE(A2,-1) -> 44985 | B3: =Passivo!C5+Passivo!D5+Passivo!E5+Passivo!K5 -> 348757.6 | C3: =Passivo!G5+Passivo!H5+Passivo!I5 -> 2668270.6 | D3: 261845.11 | E3: 346921.74 | F3: 335360.96
A4: =EDATE(A3,-1) -> 44954 | B4: =Passivo!C6+Passivo!D6+Passivo!E6+Passivo!K6 -> 338047.1 | C4: =Passivo!G6+Passivo!H6+Passivo!I6 -> 2687099 | D4: 255525.05 | E4: 344675.31 | F4: 320720.89
A5: =EDATE(A4,-1) -> 44923 | B5: =Passivo!C7+Passivo!D7+Passivo!E7+Passivo!K7 -> 311324.37 | C5: =Passivo!G7+Passivo!H7+Passivo!I7 -> 2736336 | D5: 256983.46 | E5: 342416.74 | F5: 317693.69
A6: =EDATE(A5,-1) -> 44893 | B6: =Passivo!C8+Passivo!D8+Passivo!E8+Passivo!K8 -> 322285.3 | C6: =Passivo!G8+Passivo!H8+Passivo!I8 -> 2768405.8 | D6: 257493.91 | E6: 344384.73 | F6: 349543.13
A7: =EDATE(A6,-1) -> 44862 | B7: =Passivo!C9+Passivo!D9+Passivo!E9+Passivo!K9 -> 323871.26 | C7: =Passivo!G9+Passivo!H9+Passivo!I9 -> 2795944.9 | D7: 254709.86 | E7: 344704.74 | F7: 328028.69
A8: =EDATE(A7,-1) -> 44832 | B8: =Passivo!C10+Passivo!D10+Passivo!E10+Passivo!K10 -> 322968.94 | C8: =Passivo!G10+Passivo!H10+Passivo!I10 -> 2794978.8 | D8: 252942.23 | E8: 343879.92 | F8: 335917.72
A9: =EDATE(A8,-1) -> 44801 | B9: =Passivo!C11+Passivo!D11+Passivo!E11+Passivo!K11 -> 324621.79 | C9: =Passivo!G11+Passivo!H11+Passivo!I11 -> 2822489.7 | D9: 249408.37 | E9: 338462.52 | F9: 303153.09
A10: =EDATE(A9,-1) -> 44770 | B10: =Passivo!C12+Passivo!D12+Passivo!E12+Passivo!K12 -> 320450.65 | C10: =Passivo!G12+Passivo!H12+Passivo!I12 -> 2851141.2 | D10: 248772.33 | E10: 338665.21 | F10: 276863.91
A11: =EDATE(A10,-1) -> 44740 | B11: =Passivo!C13+Passivo!D13+Passivo!E13+Passivo!K13 -> 302680 | C11: =Passivo!G13+Passivo!H13+Passivo!I13 -> 2810320.5 | D11: 249432.62 | E11: 342368.02 | F11: 317725.09
A12: =EDATE(A11,-1) -> 44709 | B12: =Passivo!C14+Passivo!D14+Passivo!E14+Passivo!K14 -> 320910.47 | C12: =Passivo!G14+Passivo!H14+Passivo!I14 -> 2881609.2 | D12: 247218.78 | E12: 340131.07 | F12: 286555.93
A13: =EDATE(A12,-1) -> 44679 | B13: =Passivo!C15+Passivo!D15+Passivo!E15+Passivo!K15 -> 323486.57 | C13: =Passivo!G15+Passivo!H15+Passivo!I15 -> 2882687.2 | D13: 248137.38 | E13: 337679.02 | F13: 272242.41
A14: =EDATE(A13,-1) -> 44648 | B14: =Passivo!C16+Passivo!D16+Passivo!E16+Passivo!K16 -> 312206.99 | C14: =Passivo!G16+Passivo!H16+Passivo!I16 -> 2842196.6 | D14: 249810.57 | E14: 345559.78 | F14: 278193.79
... A292: =EDATE(A291,-1) -> 36188 | B292: =Passivo!C294+Passivo!D294+Passivo!E294+Passivo!K294 -> 233847.6 | C292: =Passivo!G294+Passivo!H294+Passivo!I294 -> 713480.58 | D292: 251157.05 | E292: 110458.52 | F292: 289974.12

Sheet Inflation
A1: Data | B1: Inflation | C1: Revaluation Coeff
A2: 45016 | B2: 0.99580889 | C2: =1/PRODUCT(B2:$B$39) -> 0.86616162
A3: =EDATE(A2,-1) -> 44985 | B3: 1.0016793 | C3: =1/PRODUCT(B3:$B$39) -> 0.86253143
A4: =EDATE(A3,-1) -> 44954 | B4: 1.0008403 | C4: =1/PRODUCT(B4:$B$39) -> 0.86397985
A5: =EDATE(A4,-1) -> 44923 | B5: 1.0025274 | C5: =1/PRODUCT(B5:$B$39) -> 0.86470588
A6: =EDATE(A5,-1) -> 44893 | B6: 1.0050804 | C6: =1/PRODUCT(B6:$B$39) -> 0.86689132
A7: =EDATE(A6,-1) -> 44862 | B7: 1.0341506 | C7: =1/PRODUCT(B7:$B$39) -> 0.87129551
A8: =EDATE(A7,-1) -> 44832 | B8: 1.0026339 | C8: =1/PRODUCT(B8:$B$39) -> 0.90105079
A9: =EDATE(A8,-1) -> 44801 | B9: 1.0079646 | C9: =1/PRODUCT(B9:$B$39) -> 0.90342406
A10: =EDATE(A9,-1) -> 44770 | B10: 1.0044444 | C10: =1/PRODUCT(B10:$B$39) -> 0.91061947
A11: =EDATE(A10,-1) -> 44740 | B11: 1.0116906 | C11: =1/PRODUCT(B11:$B$39) -> 0.91466667
A12: =EDATE(A11,-1) -> 44709 | B12: 1.0081596 | C12: =1/PRODUCT(B12:$B$39) -> 0.92535971
A13: =EDATE(A12,-1) -> 44679 | B13: 0.9990942 | C13: =1/PRODUCT(B13:$B$39) -> 0.93291024
A14: =EDATE(A13,-1) -> 44648 | B14: 1.010064 | C14: =1/PRODUCT(B14:$B$39) -> 0.93206522
... A39: =EDATE(A38,-1) -> 43889 | B39: 0.99902818 | C39: =1/PRODUCT(B39:$B$39) -> 1.0009728
A40: =EDATE(A39,-1) -> 43858 | B40: 1.0009728 | C40: 1
A41: =EDATE(A40,-1) -> 43827 | B41: 1.0019493 | C41: =PRODUCT(B$41:$B41) -> 1.0019493
A42: =EDATE(A41,-1) -> 43797 | B42: 0.99805447 | C42: =PRODUCT(B$41:$B42) -> 1
A43: =EDATE(A42,-1) -> 43766 | B43: 0.99902818 | C43: =PRODUCT(B$41:$B43) -> 0.99902818
A44: =EDATE(A43,-1) -> 43736 | B44: 0.9942029 | C44: =PRODUCT(B$41:$B44) -> 0.99323671
A45: =EDATE(A44,-1) -> 43705 | B45: 1.0038797 | C45: =PRODUCT(B$41:$B45) -> 0.9970902
A46: =EDATE(A45,-1) -> 43674 | B46: 1 | C46: =PRODUCT(B$41:$B46) -> 0.9970902
A47: =EDATE(A46,-1) -> 43644 | B47: 1.0009709 | C47: =PRODUCT(B$41:$B47) -> 0.99805825
A48: =EDATE(A47,-1) -> 43613 | B48: 1 | C48: =PRODUCT(B$41:$B48) -> 0.99805825
A49: =EDATE(A48,-1) -> 43583 | B49: 1.0019455 | C49: =PRODUCT(B$41:$B49) -> 1
A50: =EDATE(A49,-1) -> 43552 | B50: 1.0029268 | C50: =PRODUCT(B$41:$B50) -> 1.0029268
A51: =EDATE(A50,-1) -> 43524 | B51: 1.0009766 | C51: =PRODUCT(B$41:$B51) -> 1.0039063
A52: =EDATE(A51,-1) -> 43493 | B52: 1.0009775 | C52: =PRODUCT(B$41:$B52) -> 1.0048876
... A292: =EDATE(A291,-1) -> 36188 | B292: 1.0009191 | C292: =PRODUCT(B$41:$B292) -> 1.4199722
